README.md
setup.py
mori_utils/__init__.py
mori_utils/data_operator.py
mori_utils/exception.py
mori_utils/net_works.py
mori_utils/utils.py
mori_utils/wrapper.py
mori_utils.egg-info/PKG-INFO
mori_utils.egg-info/SOURCES.txt
mori_utils.egg-info/dependency_links.txt
mori_utils.egg-info/requires.txt
mori_utils.egg-info/top_level.txt