Metadata-Version: 1.0
Name: mori-utils
Version: 0.5.6
Summary: Mori Personal Utils
Home-page: https://github.com/moriW/mori_utils
Author: moridisa
Author-email: moridisa@moridisa.cn
License: MIT
Platform: UNKNOWN
